tests/__init__.py
tests/test_core.py
youtubeinfo/__init__.py
youtubeinfo/core.py
youtubeinfo/config/__init__.py
youtubeinfo/config/constants.py
youtubeinfo-0.2.0.dist-info/licenses/LICENSE
youtubeinfo-0.2.0.dist-info/METADATA
youtubeinfo-0.2.0.dist-info/WHEEL
youtubeinfo-0.2.0.dist-info/top_level.txt
youtubeinfo-0.2.0.dist-info/RECORD
