Metadata-Version: 2.4
Name: youtubeinfo
Version: 0.2.0
Summary: Get YouTube data for analysis
Home-page: https://github.com/umLu/youtubeinfo
Author: Luiz P.
Author-email: umluiz@gmail.com
Keywords: youtube data caption
Classifier: Programming Language :: Python :: 3
Classifier: License :: OSI Approved :: GNU General Public License v3 (GPLv3)
Classifier: Operating System :: OS Independent
Classifier: Topic :: Software Development :: Libraries :: Python Modules
Requires-Python: >=3.6
License-File: LICENSE
Requires-Dist: google-api-python-client
Requires-Dist: pandas
Requires-Dist: youtube_transcript_api
Dynamic: author
Dynamic: author-email
Dynamic: classifier
Dynamic: description
Dynamic: description-content-type
Dynamic: home-page
Dynamic: keywords
Dynamic: license-file
Dynamic: requires-dist
Dynamic: requires-python
Dynamic: summary
